{
  "id": "b7318fb9-d8d0-4b10-bb65-99567e1c7c1a",
  "title": "Row y depends on available space, not row index",
  "initial": {
    "nodes": {
      "A": {
        "id": "A",
        "type": "node",
        "x": 0,
        "y": 0,
        "dimensions": {
          "x": 100,
          "y": 80
        }
      },
      "B": {
        "id": "B",
        "type": "node",
        "x": 140,
        "y": 0,
        "dimensions": {
          "x": 100,
          "y": 140
        }
      },
      "C": {
        "id": "C",
        "type": "node",
        "x": 260,
        "y": 20,
        "dimensions": {
          "x": 100,
          "y": 80
        }
      },
      "D": {
        "id": "D",
        "type": "node",
        "x": 100,
        "y": 220,
        "dimensions": {
          "x": 100,
          "y": 80
        }
      },
      "E": {
        "id": "E",
        "type": "node",
        "x": 280,
        "y": 190,
        "dimensions": {
          "x": 100,
          "y": 80
        }
      }
    },
    "edges": [
      {
        "output": {
          "node": "A",
          "port": "out"
        },
        "input": {
          "node": "B",
          "port": "in"
        }
      },
      {
        "output": {
          "node": "B",
          "port": "out"
        },
        "input": {
          "node": "C",
          "port": "in"
        }
      },
      {
        "output": {
          "node": "A",
          "port": "out"
        },
        "input": {
          "node": "D",
          "port": "in"
        }
      },
      {
        "output": {
          "node": "B",
          "port": "out"
        },
        "input": {
          "node": "E",
          "port": "in"
        }
      }
    ]
  },
  "expected": {
    "A": {
      "x": 0,
      "y": 0
    },
    "B": {
      "x": 130,
      "y": 0
    },
    "C": {
      "x": 260,
      "y": 0
    },
    "D": {
      "x": 130,
      "y": 170
    },
    "E": {
      "x": 260,
      "y": 110
    }
  }
}
