{
  "id": "cc33dd44-0001-0001-0001-cc33dd440001",
  "title": "Triple nested split-merge cascade (reconcile may need 3+ passes)",
  "initial": {
    "nodes": {
      "R": {
        "id": "R",
        "type": "node",
        "x": 0,
        "y": 400,
        "width": 100,
        "height": 80
      },
      "S1": {
        "id": "S1",
        "type": "node",
        "x": 200,
        "y": 400,
        "width": 100,
        "height": 80
      },
      "A1": {
        "id": "A1",
        "type": "node",
        "x": 400,
        "y": 350,
        "width": 100,
        "height": 80
      },
      "B1": {
        "id": "B1",
        "type": "node",
        "x": 400,
        "y": 500,
        "width": 100,
        "height": 80
      },
      "MS1": {
        "id": "MS1",
        "type": "node",
        "x": 600,
        "y": 400,
        "width": 100,
        "height": 80
      },
      "A2": {
        "id": "A2",
        "type": "node",
        "x": 800,
        "y": 350,
        "width": 100,
        "height": 80
      },
      "B2": {
        "id": "B2",
        "type": "node",
        "x": 800,
        "y": 500,
        "width": 100,
        "height": 80
      },
      "MS2": {
        "id": "MS2",
        "type": "node",
        "x": 1000,
        "y": 400,
        "width": 100,
        "height": 80
      },
      "A3": {
        "id": "A3",
        "type": "node",
        "x": 1200,
        "y": 110,
        "width": 100,
        "height": 80
      },
      "B3": {
        "id": "B3",
        "type": "node",
        "x": 1200,
        "y": 260,
        "width": 100,
        "height": 80
      },
      "M3": {
        "id": "M3",
        "type": "node",
        "x": 1400,
        "y": 0,
        "width": 100,
        "height": 80
      },
      "L": {
        "id": "L",
        "type": "node",
        "x": 1600,
        "y": 0,
        "width": 100,
        "height": 80
      },
      "X1": {
        "id": "X1",
        "type": "node",
        "x": 0,
        "y": 200,
        "width": 100,
        "height": 80
      },
      "X2": {
        "id": "X2",
        "type": "node",
        "x": 0,
        "y": 100,
        "width": 100,
        "height": 80
      },
      "X3": {
        "id": "X3",
        "type": "node",
        "x": 0,
        "y": 0,
        "width": 100,
        "height": 80
      }
    },
    "edges": {
      "R:out->S1:in": {
        "output": {
          "node": "R",
          "port": "out"
        },
        "input": {
          "node": "S1",
          "port": "in"
        }
      },
      "S1:out->A1:in": {
        "output": {
          "node": "S1",
          "port": "out"
        },
        "input": {
          "node": "A1",
          "port": "in"
        }
      },
      "S1:out->B1:in": {
        "output": {
          "node": "S1",
          "port": "out"
        },
        "input": {
          "node": "B1",
          "port": "in"
        }
      },
      "A1:out->MS1:in": {
        "output": {
          "node": "A1",
          "port": "out"
        },
        "input": {
          "node": "MS1",
          "port": "in"
        }
      },
      "B1:out->MS1:in": {
        "output": {
          "node": "B1",
          "port": "out"
        },
        "input": {
          "node": "MS1",
          "port": "in"
        }
      },
      "X1:out->MS1:in": {
        "output": {
          "node": "X1",
          "port": "out"
        },
        "input": {
          "node": "MS1",
          "port": "in"
        }
      },
      "MS1:out->A2:in": {
        "output": {
          "node": "MS1",
          "port": "out"
        },
        "input": {
          "node": "A2",
          "port": "in"
        }
      },
      "MS1:out->B2:in": {
        "output": {
          "node": "MS1",
          "port": "out"
        },
        "input": {
          "node": "B2",
          "port": "in"
        }
      },
      "A2:out->MS2:in": {
        "output": {
          "node": "A2",
          "port": "out"
        },
        "input": {
          "node": "MS2",
          "port": "in"
        }
      },
      "B2:out->MS2:in": {
        "output": {
          "node": "B2",
          "port": "out"
        },
        "input": {
          "node": "MS2",
          "port": "in"
        }
      },
      "X2:out->MS2:in": {
        "output": {
          "node": "X2",
          "port": "out"
        },
        "input": {
          "node": "MS2",
          "port": "in"
        }
      },
      "MS2:out->A3:in": {
        "output": {
          "node": "MS2",
          "port": "out"
        },
        "input": {
          "node": "A3",
          "port": "in"
        }
      },
      "MS2:out->B3:in": {
        "output": {
          "node": "MS2",
          "port": "out"
        },
        "input": {
          "node": "B3",
          "port": "in"
        }
      },
      "A3:out->M3:in": {
        "output": {
          "node": "A3",
          "port": "out"
        },
        "input": {
          "node": "M3",
          "port": "in"
        }
      },
      "B3:out->M3:in": {
        "output": {
          "node": "B3",
          "port": "out"
        },
        "input": {
          "node": "M3",
          "port": "in"
        }
      },
      "X3:out->M3:in": {
        "output": {
          "node": "X3",
          "port": "out"
        },
        "input": {
          "node": "M3",
          "port": "in"
        }
      },
      "M3:out->L:in": {
        "output": {
          "node": "M3",
          "port": "out"
        },
        "input": {
          "node": "L",
          "port": "in"
        }
      }
    }
  },
  "expected": {
    "R": {
      "x": -780,
      "y": 330
    },
    "S1": {
      "x": -650,
      "y": 330
    },
    "A1": {
      "x": -520,
      "y": 330
    },
    "B1": {
      "x": -520,
      "y": 440
    },
    "MS1": {
      "x": -390,
      "y": 220
    },
    "A2": {
      "x": -260,
      "y": 220
    },
    "B2": {
      "x": -260,
      "y": 330
    },
    "MS2": {
      "x": -130,
      "y": 110
    },
    "A3": {
      "x": 0,
      "y": 110
    },
    "B3": {
      "x": 0,
      "y": 220
    },
    "M3": {
      "x": 130,
      "y": 0
    },
    "L": {
      "x": 260,
      "y": 0
    },
    "X1": {
      "x": -520,
      "y": 220
    },
    "X2": {
      "x": -260,
      "y": 110
    },
    "X3": {
      "x": 0,
      "y": 0
    }
  }
}